{"timestamp": 1656, "object_list": [{"position": [0.08, 0.22], "id": 356}, {"position": [-0.72, -6.71], "id": 361}, {"position": [-0.68, 2.66], "id": 369}, {"position": [-0.6, 3.24], "id": 371}, {"position": [2.78, 2.09], "id": 382}, {"position": [3.44, 2.3], "id": 383}, {"position": [1.53, -7.95], "id": 385}, {"position": [1.43, 3.16], "id": 386}, {"position": [1.01, -0.55], "id": 387}, {"position": [2.77, -5.13], "id": 388}, {"position": [3.5, -5.25], "id": 389}, {"position": [3.82, -1.84], "id": 390}], "frame": 1656, "size": 12}