{"timestamp": 961, "object_list": [{"position": [-1.09, -6.72], "id": 180}, {"position": [2.01, 3.01], "id": 181}, {"position": [2.76, 3.23], "id": 182}, {"position": [-0.86, -1.08], "id": 185}, {"position": [1.39, -9.67], "id": 187}, {"position": [0.88, -7.88], "id": 190}, {"position": [1.5, -5.79], "id": 192}, {"position": [0.63, -6.29], "id": 193}, {"position": [2.14, -2.5], "id": 194}, {"position": [2.55, -2.75], "id": 195}, {"position": [1.16, -2.75], "id": 196}, {"position": [-0.3, -4.21], "id": 199}, {"position": [2.12, -6.46], "id": 200}, {"position": [2.86, -6.58], "id": 201}, {"position": [0.95, 3.07], "id": 203}, {"position": [-0.12, -5.85], "id": 204}], "frame": 961, "size": 16}