{"timestamp": 968, "object_list": [{"position": [-1.11, -6.7], "id": 180}, {"position": [-0.89, -0.98], "id": 185}, {"position": [1.69, 1.29], "id": 194}, {"position": [2.24, 1.29], "id": 195}, {"position": [1.52, -7.23], "id": 196}, {"position": [-0.22, -4.18], "id": 199}, {"position": [1.79, -2.42], "id": 200}, {"position": [2.51, -2.62], "id": 201}, {"position": [0.6, -0.43], "id": 203}, {"position": [-1.36, -5.8], "id": 204}, {"position": [3.4, -2.14], "id": 205}, {"position": [1.16, 2.94], "id": 206}, {"position": [-0.19, 2.81], "id": 207}, {"position": [-0.76, 3.03], "id": 208}], "frame": 968, "size": 14}